comcigan/__init__.py
comcigan/comcigan.py
python_comcigan-1.0.4.dist-info/LICENSE
python_comcigan-1.0.4.dist-info/METADATA
python_comcigan-1.0.4.dist-info/WHEEL
python_comcigan-1.0.4.dist-info/top_level.txt
python_comcigan-1.0.4.dist-info/RECORD
