Metadata-Version: 2.1
Name: python-comcigan
Version: 1.0.4
Summary: Comcigan api for Python
Home-page: https://github.com/H2Owater425/python-comcigan
Author: H2Owater425
Author-email: h2o@h2owr.xyz
License: MIT
Platform: UNKNOWN
Classifier: Programming Language :: Python :: 3
Classifier: License :: OSI Approved :: MIT License
Classifier: Operating System :: OS Independent
Requires-Python: >=3.7
